{
  "timestamp": "2025-09-28T17:00:18.622Z",
  "summary": {
    "totalErrors": 2,
    "totalWarnings": 0,
    "totalTimeouts": 0,
    "criticalIssues": 0
  },
  "errors": [
    {
      "type": "NAVIGATION_ERROR",
      "message": "Échec navigation catalogue: page.click: Timeout 8000ms exceeded.\nCall log:\n\u001b[2m  - waiting for locator('a[href=\"/catalogue\"]')\u001b[22m\n",
      "timestamp": "2025-09-28T17:00:08.906Z"
    },
    {
      "type": "NAVIGATION_ERROR",
      "message": "Échec navigation dashboard: page.click: Timeout 8000ms exceeded.\nCall log:\n\u001b[2m  - waiting for locator('a[href=\"/dashboard\"]')\u001b[22m\n",
      "timestamp": "2025-09-28T17:00:16.913Z"
    }
  ],
  "warnings": [],
  "timeouts": [],
  "recommendations": []
}